CHANGES.rst
CONTRIBUTORS.rst
MANIFEST.in
README.rst
setup.cfg
setup.py
docs/LICENSE.GPL
docs/LICENSE.rst
docs/index.rst
src/collective/__init__.py
src/collective.z3cform.select2.egg-info/PKG-INFO
src/collective.z3cform.select2.egg-info/SOURCES.txt
src/collective.z3cform.select2.egg-info/dependency_links.txt
src/collective.z3cform.select2.egg-info/entry_points.txt
src/collective.z3cform.select2.egg-info/namespace_packages.txt
src/collective.z3cform.select2.egg-info/not-zip-safe
src/collective.z3cform.select2.egg-info/requires.txt
src/collective.z3cform.select2.egg-info/top_level.txt
src/collective/z3cform/__init__.py
src/collective/z3cform/select2/__init__.py
src/collective/z3cform/select2/configure.zcml
src/collective/z3cform/select2/interfaces.py
src/collective/z3cform/select2/minimal.zcml
src/collective/z3cform/select2/testing.py
src/collective/z3cform/select2/browser/__init__.py
src/collective/z3cform/select2/browser/configure.zcml
src/collective/z3cform/select2/browser/select2widget.py
src/collective/z3cform/select2/browser/static/select2-widget.css
src/collective/z3cform/select2/browser/static/select2-widget.js
src/collective/z3cform/select2/browser/templates/select2-view.js
src/collective/z3cform/select2/browser/templates/select2.pt
src/collective/z3cform/select2/locales/collective.z3cform.select2.pot
src/collective/z3cform/select2/locales/update.sh
src/collective/z3cform/select2/profiles/default/browserlayer.xml
src/collective/z3cform/select2/profiles/default/collectivez3cformselect2_default.txt
src/collective/z3cform/select2/profiles/default/cssregistry.xml
src/collective/z3cform/select2/profiles/default/jsregistry.xml
src/collective/z3cform/select2/profiles/default/metadata.xml
src/collective/z3cform/select2/tests/__init__.py
src/collective/z3cform/select2/tests/test_robot.py
src/collective/z3cform/select2/tests/test_setup.py
src/collective/z3cform/select2/tests/test_widgets.py
src/collective/z3cform/select2/tests/robot/test_example.robot
src/collective/z3cform/select2/widget/__init__.py
src/collective/z3cform/select2/widget/adapters.zcml
src/collective/z3cform/select2/widget/bootstrap.zcml
src/collective/z3cform/select2/widget/configure.zcml
src/collective/z3cform/select2/widget/multi_select2_input.pt
src/collective/z3cform/select2/widget/single_select2_input.pt
src/collective/z3cform/select2/widget/widget.py
src/collective/z3cform/select2/widget/widget_display.pt
