Metadata-Version: 1.1
Name: collective.z3cform.select2
Version: 1.4.1
Summary: select2 widget for z3c.form and eea.facetednavigation
Home-page: https://pypi.python.org/pypi/collective.z3cform.select2
Author: Vincent Fretin
Author-email: vincent.fretin@gmail.com
License: GPL version 2
Keywords: Python Plone
Platform: UNKNOWN
Classifier: Environment :: Web Environment
Classifier: Framework :: Plone
Classifier: Framework :: Plone :: 4.3
Classifier: Programming Language :: Python
Classifier: Programming Language :: Python :: 2.7
Classifier: Operating System :: OS Independent
Classifier: License :: OSI Approved :: GNU General Public License v2 (GPLv2)
